test_run_dir.old/mm2hdmi.MM2hdmiTester1155991862/MM2hdmi.v
module MM2hdmi(
  input         clock,
  input         reset,
  input  [15:0] io_data,
  input         io_newData,
  output [7:0]  io_red,
  output [7:0]  io_blue,
  output [7:0]  io_green,
  output        io_vSync,
  output        io_hSync
);
`ifdef RANDOMIZE_REG_INIT
  reg [31:0] _RAND_0;
  reg [31:0] _RAND_1;
  reg [31:0] _RAND_2;
  reg [31:0] _RAND_3;
  reg [31:0] _RAND_4;
  reg [31:0] _RAND_5;
  reg [31:0] _RAND_6;
  reg [31:0] _RAND_7;
  reg [31:0] _RAND_8;
  reg [31:0] _RAND_9;
  reg [31:0] _RAND_10;
  reg [31:0] _RAND_11;
  reg [31:0] _RAND_12;
  reg [31:0] _RAND_13;
  reg [31:0] _RAND_14;
  reg [31:0] _RAND_15;
  reg [31:0] _RAND_16;
  reg [31:0] _RAND_17;
  reg [31:0] _RAND_18;
  reg [31:0] _RAND_19;
  reg [31:0] _RAND_20;
  reg [31:0] _RAND_21;
`endif // RANDOMIZE_REG_INIT
  reg  regNewData; // @[mm2hdmi.scala 19:27]
  reg  regHSync; // @[mm2hdmi.scala 21:25]
  wire  _T_1 = regHSync + 1'h1; // @[mm2hdmi.scala 22:24]
  reg [4:0] regRow; // @[mm2hdmi.scala 24:23]
  wire [4:0] _T_4 = regRow + 5'h1; // @[mm2hdmi.scala 26:22]
  reg  regVSync; // @[mm2hdmi.scala 29:25]
  wire  _T_5 = regRow == 5'h1f; // @[mm2hdmi.scala 30:15]
  wire  _T_7 = _T_5 & io_newData; // @[mm2hdmi.scala 30:24]
  wire  _T_9 = regVSync + 1'h1; // @[mm2hdmi.scala 31:26]
  wire  _GEN_1 = _T_7 & _T_9; // @[mm2hdmi.scala 30:47]
  reg [15:0] regData; // @[mm2hdmi.scala 37:24]
  wire  _T_11 = ~regData[0]; // @[mm2hdmi.scala 39:43]
  reg [7:0] regMuxRed0; // @[mm2hdmi.scala 39:27]
  wire  _T_14 = ~regData[1]; // @[mm2hdmi.scala 40:43]
  reg [7:0] regMuxRed1; // @[mm2hdmi.scala 40:27]
  wire  _T_17 = ~regData[2]; // @[mm2hdmi.scala 41:43]
  reg [7:0] regMuxRed2; // @[mm2hdmi.scala 41:27]
  wire  _T_20 = ~regData[3]; // @[mm2hdmi.scala 42:43]
  reg [7:0] regMuxRed3; // @[mm2hdmi.scala 42:27]
  wire  _T_23 = ~regData[4]; // @[mm2hdmi.scala 43:43]
  reg [7:0] regMuxRed4; // @[mm2hdmi.scala 43:27]
  wire  _T_26 = ~regData[5]; // @[mm2hdmi.scala 44:43]
  reg [7:0] regMuxRed5; // @[mm2hdmi.scala 44:27]
  wire  _T_29 = ~regData[6]; // @[mm2hdmi.scala 45:43]
  reg [7:0] regMuxRed6; // @[mm2hdmi.scala 45:27]
  wire  _T_32 = ~regData[7]; // @[mm2hdmi.scala 46:43]
  reg [7:0] regMuxRed7; // @[mm2hdmi.scala 46:27]
  wire  _T_35 = ~regData[8]; // @[mm2hdmi.scala 47:43]
  reg [7:0] regMuxRed8; // @[mm2hdmi.scala 47:27]
  wire  _T_38 = ~regData[9]; // @[mm2hdmi.scala 48:43]
  reg [7:0] regMuxRed9; // @[mm2hdmi.scala 48:27]
  wire  _T_41 = ~regData[10]; // @[mm2hdmi.scala 49:45]
  reg [7:0] regMuxRed10; // @[mm2hdmi.scala 49:28]
  wire  _T_44 = ~regData[11]; // @[mm2hdmi.scala 50:45]
  reg [7:0] regMuxRed11; // @[mm2hdmi.scala 50:28]
  wire  _T_47 = ~regData[12]; // @[mm2hdmi.scala 51:45]
  reg [7:0] regMuxRed12; // @[mm2hdmi.scala 51:28]
  wire  _T_50 = ~regData[13]; // @[mm2hdmi.scala 52:45]
  reg [7:0] regMuxRed13; // @[mm2hdmi.scala 52:28]
  wire  _T_53 = ~regData[14]; // @[mm2hdmi.scala 53:45]
  reg [7:0] regMuxRed14; // @[mm2hdmi.scala 53:28]
  wire  _T_56 = ~regData[15]; // @[mm2hdmi.scala 54:45]
  reg [7:0] regMuxRed15; // @[mm2hdmi.scala 54:28]
  reg [3:0] outControlCounter; // @[mm2hdmi.scala 56:34]
  wire  _T_58 = outControlCounter == 4'hf; // @[mm2hdmi.scala 57:46]
  wire  _T_60 = _T_58 | regNewData; // @[mm2hdmi.scala 57:55]
  wire [3:0] _T_62 = outControlCounter + 4'h1; // @[mm2hdmi.scala 57:101]
  wire  _T_64 = outControlCounter == 4'h0; // @[mm2hdmi.scala 59:27]
  wire  _T_65 = outControlCounter == 4'h1; // @[mm2hdmi.scala 64:32]
  wire  _T_66 = outControlCounter == 4'h2; // @[mm2hdmi.scala 69:32]
  wire  _T_67 = outControlCounter == 4'h3; // @[mm2hdmi.scala 74:32]
  wire  _T_68 = outControlCounter == 4'h4; // @[mm2hdmi.scala 79:32]
  wire  _T_69 = outControlCounter == 4'h5; // @[mm2hdmi.scala 84:32]
  wire  _T_70 = outControlCounter == 4'h6; // @[mm2hdmi.scala 89:32]
  wire  _T_71 = outControlCounter == 4'h7; // @[mm2hdmi.scala 94:32]
  wire  _T_72 = outControlCounter == 4'h8; // @[mm2hdmi.scala 99:32]
  wire  _T_73 = outControlCounter == 4'h9; // @[mm2hdmi.scala 104:32]
  wire  _T_74 = outControlCounter == 4'ha; // @[mm2hdmi.scala 109:32]
  wire  _T_75 = outControlCounter == 4'hb; // @[mm2hdmi.scala 114:32]
  wire  _T_76 = outControlCounter == 4'hc; // @[mm2hdmi.scala 119:32]
  wire  _T_77 = outControlCounter == 4'hd; // @[mm2hdmi.scala 124:32]
  wire  _T_78 = outControlCounter == 4'he; // @[mm2hdmi.scala 129:32]
  wire [7:0] _GEN_2 = _T_78 ? regMuxRed14 : regMuxRed15; // @[mm2hdmi.scala 129:42]
  wire [7:0] _GEN_3 = _T_77 ? regMuxRed13 : _GEN_2; // @[mm2hdmi.scala 124:42]
  wire [7:0] _GEN_4 = _T_76 ? regMuxRed12 : _GEN_3; // @[mm2hdmi.scala 119:42]
  wire [7:0] _GEN_5 = _T_75 ? regMuxRed11 : _GEN_4; // @[mm2hdmi.scala 114:42]
  wire [7:0] _GEN_6 = _T_74 ? regMuxRed10 : _GEN_5; // @[mm2hdmi.scala 109:42]
  wire [7:0] _GEN_7 = _T_73 ? regMuxRed9 : _GEN_6; // @[mm2hdmi.scala 104:41]
  wire [7:0] _GEN_8 = _T_72 ? regMuxRed8 : _GEN_7; // @[mm2hdmi.scala 99:41]
  wire [7:0] _GEN_9 = _T_71 ? regMuxRed7 : _GEN_8; // @[mm2hdmi.scala 94:41]
  wire [7:0] _GEN_10 = _T_70 ? regMuxRed6 : _GEN_9; // @[mm2hdmi.scala 89:41]
  wire [7:0] _GEN_11 = _T_69 ? regMuxRed5 : _GEN_10; // @[mm2hdmi.scala 84:41]
  wire [7:0] _GEN_12 = _T_68 ? regMuxRed4 : _GEN_11; // @[mm2hdmi.scala 79:41]
  wire [7:0] _GEN_13 = _T_67 ? regMuxRed3 : _GEN_12; // @[mm2hdmi.scala 74:41]
  wire [7:0] _GEN_14 = _T_66 ? regMuxRed2 : _GEN_13; // @[mm2hdmi.scala 69:41]
  wire [7:0] _GEN_15 = _T_65 ? regMuxRed1 : _GEN_14; // @[mm2hdmi.scala 64:41]
  assign io_red = _T_64 ? regMuxRed0 : _GEN_15; // @[mm2hdmi.scala 60:12 mm2hdmi.scala 65:12 mm2hdmi.scala 70:12 mm2hdmi.scala 75:12 mm2hdmi.scala 80:12 mm2hdmi.scala 85:12 mm2hdmi.scala 90:12 mm2hdmi.scala 95:12 mm2hdmi.scala 100:12 mm2hdmi.scala 105:12 mm2hdmi.scala 110:12 mm2hdmi.scala 115:12 mm2hdmi.scala 120:12 mm2hdmi.scala 125:12 mm2hdmi.scala 130:12 mm2hdmi.scala 135:12]
  assign io_blue = _T_64 ? regMuxRed0 : _GEN_15; // @[mm2hdmi.scala 62:13 mm2hdmi.scala 67:13 mm2hdmi.scala 72:13 mm2hdmi.scala 77:13 mm2hdmi.scala 82:13 mm2hdmi.scala 87:13 mm2hdmi.scala 92:13 mm2hdmi.scala 97:13 mm2hdmi.scala 102:13 mm2hdmi.scala 107:13 mm2hdmi.scala 112:13 mm2hdmi.scala 117:13 mm2hdmi.scala 122:13 mm2hdmi.scala 127:13 mm2hdmi.scala 132:13 mm2hdmi.scala 137:13]
  assign io_green = _T_64 ? regMuxRed0 : _GEN_15; // @[mm2hdmi.scala 61:14 mm2hdmi.scala 66:14 mm2hdmi.scala 71:14 mm2hdmi.scala 76:14 mm2hdmi.scala 81:14 mm2hdmi.scala 86:14 mm2hdmi.scala 91:14 mm2hdmi.scala 96:14 mm2hdmi.scala 101:14 mm2hdmi.scala 106:14 mm2hdmi.scala 111:14 mm2hdmi.scala 116:14 mm2hdmi.scala 121:14 mm2hdmi.scala 126:14 mm2hdmi.scala 131:14 mm2hdmi.scala 136:14]
  assign io_vSync = regVSync; // @[mm2hdmi.scala 141:12]
  assign io_hSync = regHSync; // @[mm2hdmi.scala 140:12]
`ifdef RANDOMIZE_GARBAGE_ASSIGN
`define RANDOMIZE
`endif
`ifdef RANDOMIZE_INVALID_ASSIGN
`define RANDOMIZE
`endif
`ifdef RANDOMIZE_REG_INIT
`define RANDOMIZE
`endif
`ifdef RANDOMIZE_MEM_INIT
`define RANDOMIZE
`endif
`ifndef RANDOM
`define RANDOM $random
`endif
`ifdef RANDOMIZE_MEM_INIT
  integer initvar;
`endif
`ifndef SYNTHESIS
`ifdef FIRRTL_BEFORE_INITIAL
`FIRRTL_BEFORE_INITIAL
`endif
initial begin
  `ifdef RANDOMIZE
    `ifdef INIT_RANDOM
      `INIT_RANDOM
    `endif
    `ifndef VERILATOR
      `ifdef RANDOMIZE_DELAY
        #`RANDOMIZE_DELAY begin end
      `else
        #0.002 begin end
      `endif
    `endif
`ifdef RANDOMIZE_REG_INIT
  _RAND_0 = {1{`RANDOM}};
  regNewData = _RAND_0[0:0];
  _RAND_1 = {1{`RANDOM}};
  regHSync = _RAND_1[0:0];
  _RAND_2 = {1{`RANDOM}};
  regRow = _RAND_2[4:0];
  _RAND_3 = {1{`RANDOM}};
  regVSync = _RAND_3[0:0];
  _RAND_4 = {1{`RANDOM}};
  regData = _RAND_4[15:0];
  _RAND_5 = {1{`RANDOM}};
  regMuxRed0 = _RAND_5[7:0];
  _RAND_6 = {1{`RANDOM}};
  regMuxRed1 = _RAND_6[7:0];
  _RAND_7 = {1{`RANDOM}};
  regMuxRed2 = _RAND_7[7:0];
  _RAND_8 = {1{`RANDOM}};
  regMuxRed3 = _RAND_8[7:0];
  _RAND_9 = {1{`RANDOM}};
  regMuxRed4 = _RAND_9[7:0];
  _RAND_10 = {1{`RANDOM}};
  regMuxRed5 = _RAND_10[7:0];
  _RAND_11 = {1{`RANDOM}};
  regMuxRed6 = _RAND_11[7:0];
  _RAND_12 = {1{`RANDOM}};
  regMuxRed7 = _RAND_12[7:0];
  _RAND_13 = {1{`RANDOM}};
  regMuxRed8 = _RAND_13[7:0];
  _RAND_14 = {1{`RANDOM}};
  regMuxRed9 = _RAND_14[7:0];
  _RAND_15 = {1{`RANDOM}};
  regMuxRed10 = _RAND_15[7:0];
  _RAND_16 = {1{`RANDOM}};
  regMuxRed11 = _RAND_16[7:0];
  _RAND_17 = {1{`RANDOM}};
  regMuxRed12 = _RAND_17[7:0];
  _RAND_18 = {1{`RANDOM}};
  regMuxRed13 = _RAND_18[7:0];
  _RAND_19 = {1{`RANDOM}};
  regMuxRed14 = _RAND_19[7:0];
  _RAND_20 = {1{`RANDOM}};
  regMuxRed15 = _RAND_20[7:0];
  _RAND_21 = {1{`RANDOM}};
  outControlCounter = _RAND_21[3:0];
`endif // RANDOMIZE_REG_INIT
  `endif // RANDOMIZE
end // initial
`ifdef FIRRTL_AFTER_INITIAL
`FIRRTL_AFTER_INITIAL
`endif
`endif // SYNTHESIS
  always @(posedge clock) begin
    regNewData <= io_newData;
    if (reset) begin
      regHSync <= 1'h0;
    end else begin
      regHSync <= _T_1;
    end
    if (reset) begin
      regRow <= 5'h0;
    end else if (io_newData) begin
      regRow <= _T_4;
    end
    if (reset) begin
      regVSync <= 1'h0;
    end else begin
      regVSync <= _GEN_1;
    end
    regData <= io_data;
    if (_T_11) begin
      regMuxRed0 <= 8'h0;
    end else begin
      regMuxRed0 <= 8'hff;
    end
    if (_T_14) begin
      regMuxRed1 <= 8'h0;
    end else begin
      regMuxRed1 <= 8'hff;
    end
    if (_T_17) begin
      regMuxRed2 <= 8'h0;
    end else begin
      regMuxRed2 <= 8'hff;
    end
    if (_T_20) begin
      regMuxRed3 <= 8'h0;
    end else begin
      regMuxRed3 <= 8'hff;
    end
    if (_T_23) begin
      regMuxRed4 <= 8'h0;
    end else begin
      regMuxRed4 <= 8'hff;
    end
    if (_T_26) begin
      regMuxRed5 <= 8'h0;
    end else begin
      regMuxRed5 <= 8'hff;
    end
    if (_T_29) begin
      regMuxRed6 <= 8'h0;
    end else begin
      regMuxRed6 <= 8'hff;
    end
    if (_T_32) begin
      regMuxRed7 <= 8'h0;
    end else begin
      regMuxRed7 <= 8'hff;
    end
    if (_T_35) begin
      regMuxRed8 <= 8'h0;
    end else begin
      regMuxRed8 <= 8'hff;
    end
    if (_T_38) begin
      regMuxRed9 <= 8'h0;
    end else begin
      regMuxRed9 <= 8'hff;
    end
    if (_T_41) begin
      regMuxRed10 <= 8'h0;
    end else begin
      regMuxRed10 <= 8'hff;
    end
    if (_T_44) begin
      regMuxRed11 <= 8'h0;
    end else begin
      regMuxRed11 <= 8'hff;
    end
    if (_T_47) begin
      regMuxRed12 <= 8'h0;
    end else begin
      regMuxRed12 <= 8'hff;
    end
    if (_T_50) begin
      regMuxRed13 <= 8'h0;
    end else begin
      regMuxRed13 <= 8'hff;
    end
    if (_T_53) begin
      regMuxRed14 <= 8'h0;
    end else begin
      regMuxRed14 <= 8'hff;
    end
    if (_T_56) begin
      regMuxRed15 <= 8'h0;
    end else begin
      regMuxRed15 <= 8'hff;
    end
    if (reset) begin
      outControlCounter <= 4'h0;
    end else if (_T_60) begin
      outControlCounter <= 4'h0;
    end else begin
      outControlCounter <= _T_62;
    end
  end
endmodule

test_run_dir.old/mm2hdmi.MM2hdmiTester168787131/MM2hdmi.vcd
$version Generated by VerilatedVcd $end
$date Tue Dec  1 23:48:43 2020
 $end
$timescale   1ns $end

 $scope module TOP $end
  $var wire  1 8 clock $end
  $var wire 16 : io_data [15:0] $end
  $var wire  1 > io_hSync $end
  $var wire  1 ; io_newData $end
  $var wire  8 < io_red [7:0] $end
  $var wire  1 = io_vSync $end
  $var wire  1 9 reset $end
  $scope module MM2hdmi $end
   $var wire  1 8 clock $end
   $var wire 16 : io_data [15:0] $end
   $var wire  1 > io_hSync $end
   $var wire  1 ; io_newData $end
   $var wire  8 < io_red [7:0] $end
   $var wire  1 = io_vSync $end
   $var wire  4 7 outControlCounter [3:0] $end
   $var wire 16 & regData [15:0] $end
   $var wire  8 ' regMuxRed0 [7:0] $end
   $var wire  8 ( regMuxRed1 [7:0] $end
   $var wire  8 1 regMuxRed10 [7:0] $end
   $var wire  8 2 regMuxRed11 [7:0] $end
   $var wire  8 3 regMuxRed12 [7:0] $end
   $var wire  8 4 regMuxRed13 [7:0] $end
   $var wire  8 5 regMuxRed14 [7:0] $end
   $var wire  8 6 regMuxRed15 [7:0] $end
   $var wire  8 ) regMuxRed2 [7:0] $end
   $var wire  8 * regMuxRed3 [7:0] $end
   $var wire  8 + regMuxRed4 [7:0] $end
   $var wire  8 , regMuxRed5 [7:0] $end
   $var wire  8 - regMuxRed6 [7:0] $end
   $var wire  8 . regMuxRed7 [7:0] $end
   $var wire  8 / regMuxRed8 [7:0] $end
   $var wire  8 0 regMuxRed9 [7:0] $end
   $var wire  1 # regNewData $end
   $var wire  5 $ regRow [4:0] $end
   $var wire  1 % regVSync $end
   $var wire  1 9 reset $end
  $upscope $end
 $upscope $end
$enddefinitions $end


#0
0#
b00000 $
0%
b0000000000000000 &
b00000000 '
b00000000 (
b00000000 )
b00000000 *
b00000000 +
b00000000 ,
b00000000 -
b00000000 .
b00000000 /
b00000000 0
b00000000 1
b00000000 2
b00000000 3
b00000000 4
b00000000 5
b00000000 6
b0000 7
08
19
b0000000000000000 :
0;
b00000000 <
0=
0>
#1
18
#2
08
#3
18
#4
08
#5
18
#6
08
#7
18
#8
08
#9
18
#10
08
09
b0000000000000001 :
1;
#11
1#
b00001 $
b0000000000000001 &
b0001 7
18
1>
#12
08
0;
#13
0#
b11111111 '
b0000 7
18
b11111111 <
0>
#14
08
#15
b0001 7
18
b00000000 <
#16
08
#17
b0010 7
18
#18
08
#19
b0011 7
18
#20
08
#21
b0100 7
18
#22
08
#23
b0101 7
18
#24
08
#25
b0110 7
18
#26
08
#27
b0111 7
18
#28
08
#29
b1000 7
18
#30
08
#31
b1001 7
18
#32
08
#33
b1010 7
18
#34
08
#35
b1011 7
18
#36
08
#37
b1100 7
18
#38
08
#39
b1101 7
18
#40
08
#41
b1110 7
18
#42
08
#43
b1111 7
18
#44
08
b0000000000000010 :
1;
#45
1#
b00010 $
b0000000000000010 &
b0000 7
18
b11111111 <
1>
#46
08
0;
#47
0#
b00000000 '
b11111111 (
18
b00000000 <
0>
#48
08
#49
b0001 7
18
b11111111 <
#50
08
#51
b0010 7
18
b00000000 <
#52
08
#53
b0011 7
18
#54
08
#55
b0100 7
18
#56
08
#57
b0101 7
18
#58
08
#59
b0110 7
18
#60
08
#61
b0111 7
18
#62
08
#63
b1000 7
18
#64
08
#65
b1001 7
18
#66
08
#67
b1010 7
18
#68
08
#69
b1011 7
18
#70
08
#71
b1100 7
18
#72
08
#73
b1101 7
18
#74
08
#75
b1110 7
18
#76
08
#77
b1111 7
18
#78
08
b0000000000000011 :
1;
#79
1#
b00011 $
b0000000000000011 &
b0000 7
18
1>
#80
08
0;
#81
0#
b11111111 '
18
b11111111 <
0>
#82
08
#83
b0001 7
18
#84
08
#85
b0010 7
18
b00000000 <
#86
08
#87
b0011 7
18
#88
08
#89
b0100 7
18
#90
08
#91
b0101 7
18
#92
08
#93
b0110 7
18
#94
08
#95
b0111 7
18
#96
08
#97
b1000 7
18
#98
08
#99
b1001 7
18
#100
08
#101
b1010 7
18
#102
08
#103
b1011 7
18
#104
08
#105
b1100 7
18
#106
08
#107
b1101 7
18
#108
08
#109
b1110 7
18
#110
08
#111
b1111 7
18
#112
08
b0000000000000100 :
1;
#113
1#
b00100 $
b0000000000000100 &
b0000 7
18
b11111111 <
1>
#114
08
0;
#115
0#
b00000000 '
b00000000 (
b11111111 )
18
b00000000 <
0>
#116
08
#117
b0001 7
18
#118
08
#119
b0010 7
18
b11111111 <
#120
08
#121
b0011 7
18
b00000000 <
#122
08
#123
b0100 7
18
#124
08
#125
b0101 7
18
#126
08
#127
b0110 7
18
#128
08
#129
b0111 7
18
#130
08
#131
b1000 7
18
#132
08
#133
b1001 7
18
#134
08
#135
b1010 7
18
#136
08
#137
b1011 7
18
#138
08
#139
b1100 7
18
#140
08
#141
b1101 7
18
#142
08
#143
b1110 7
18
#144
08
#145
b1111 7
18
#146
08
b0000000000000101 :
1;
#147
1#
b00101 $
b0000000000000101 &
b0000 7
18
1>
#148
08
0;
#149
0#
b11111111 '
18
b11111111 <
0>
#150
08
#151
b0001 7
18
b00000000 <
#152
08
#153
b0010 7
18
b11111111 <
#154
08
#155
b0011 7
18
b00000000 <
#156
08
#157
b0100 7
18
#158
08
#159
b0101 7
18
#160
08
#161
b0110 7
18
#162
08
#163
b0111 7
18
#164
08
#165
b1000 7
18
#166
08
#167
b1001 7
18
#168
08
#169
b1010 7
18
#170
08
#171
b1011 7
18
#172
08
#173
b1100 7
18
#174
08
#175
b1101 7
18
#176
08
#177
b1110 7
18
#178
08
#179
b1111 7
18
#180
08
b0000000000000110 :
1;
#181
1#
b00110 $
b0000000000000110 &
b0000 7
18
b11111111 <
1>
#182
08
0;
#183
0#
b00000000 '
b11111111 (
18
b00000000 <
0>
#184
08
#185
b0001 7
18
b11111111 <
#186
08
#187
b0010 7
18
#188
08
#189
b0011 7
18
b00000000 <
#190
08
#191
b0100 7
18
#192
08
#193
b0101 7
18
#194
08
#195
b0110 7
18
#196
08
#197
b0111 7
18
#198
08
#199
b1000 7
18
#200
08
#201
b1001 7
18
#202
08
#203
b1010 7
18
#204
08
#205
b1011 7
18
#206
08
#207
b1100 7
18
#208
08
#209
b1101 7
18
#210
08
#211
b1110 7
18
#212
08
#213
b1111 7
18
#214
08
b0000000000000111 :
1;
#215
1#
b00111 $
b0000000000000111 &
b0000 7
18
1>
#216
08
0;
#217
0#
b11111111 '
18
b11111111 <
0>
#218
08
#219
b0001 7
18
#220
08
#221
b0010 7
18
#222
08
#223
b0011 7
18
b00000000 <
#224
08
#225
b0100 7
18
#226
08
#227
b0101 7
18
#228
08
#229
b0110 7
18
#230
08
#231
b0111 7
18
#232
08
#233
b1000 7
18
#234
08
#235
b1001 7
18
#236
08
#237
b1010 7
18
#238
08
#239
b1011 7
18
#240
08
#241
b1100 7
18
#242
08
#243
b1101 7
18
#244
08
#245
b1110 7
18
#246
08
#247
b1111 7
18
#248
08
b0000000000001000 :
1;
#249
1#
b01000 $
b0000000000001000 &
b0000 7
18
b11111111 <
1>
#250
08
0;
#251
0#
b00000000 '
b00000000 (
b00000000 )
b11111111 *
18
b00000000 <
0>
#252
08
#253
b0001 7
18
#254
08
#255
b0010 7
18
#256
08
#257
b0011 7
18
b11111111 <
#258
08
#259
b0100 7
18
b00000000 <
#260
08
#261
b0101 7
18
#262
08
#263
b0110 7
18
#264
08
#265
b0111 7
18
#266
08
#267
b1000 7
18
#268
08
#269
b1001 7
18
#270
08
#271
b1010 7
18
#272
08
#273
b1011 7
18
#274
08
#275
b1100 7
18
#276
08
#277
b1101 7
18
#278
08
#279
b1110 7
18
#280
08
#281
b1111 7
18
#282
08
b0000000000001001 :
1;
#283
1#
b01001 $
b0000000000001001 &
b0000 7
18
1>
#284
08
0;
#285
0#
b11111111 '
18
b11111111 <
0>
#286
08
#287
b0001 7
18
b00000000 <
#288
08
#289
b0010 7
18
#290
08
#291
b0011 7
18
b11111111 <
#292
08
#293
b0100 7
18
b00000000 <
#294
08
#295
b0101 7
18
#296
08
#297
b0110 7
18
#298
08
#299
b0111 7
18
#300
08
#301
b1000 7
18
#302
08
#303
b1001 7
18
#304
08
#305
b1010 7
18
#306
08
#307
b1011 7
18
#308
08
#309
b1100 7
18
#310
08
#311
b1101 7
18
#312
08
#313
b1110 7
18
#314
08
#315
b1111 7
18
#316
08
b0000000000001010 :
1;
#317
1#
b01010 $
b0000000000001010 &
b0000 7
18
b11111111 <
1>
#318
08
0;
#319
0#
b00000000 '
b11111111 (
18
b00000000 <
0>
#320
08
#321
b0001 7
18
b11111111 <
#322
08
#323
b0010 7
18
b00000000 <
#324
08
#325
b0011 7
18
b11111111 <
#326
08
#327
b0100 7
18
b00000000 <
#328
08
#329
b0101 7
18
#330
08
#331
b0110 7
18
#332
08
#333
b0111 7
18
#334
08
#335
b1000 7
18
#336
08
#337
b1001 7
18
#338
08
#339
b1010 7
18
#340
08
#341
b1011 7
18
#342
08
#343
b1100 7
18
#344
08
#345
b1101 7
18
#346
08
#347
b1110 7
18
#348
08
#349
b1111 7
18
#350
08
b0000000000001011 :
1;
#351
1#
b01011 $
b0000000000001011 &
b0000 7
18
1>
#352
08
0;
#353
0#
b11111111 '
18
b11111111 <
0>
#354
08
#355
b0001 7
18
#356
08
#357
b0010 7
18
b00000000 <
#358
08
#359
b0011 7
18
b11111111 <
#360
08
#361
b0100 7
18
b00000000 <
#362
08
#363
b0101 7
18
#364
08
#365
b0110 7
18
#366
08
#367
b0111 7
18
#368
08
#369
b1000 7
18
#370
08
#371
b1001 7
18
#372
08
#373
b1010 7
18
#374
08
#375
b1011 7
18
#376
08
#377
b1100 7
18
#378
08
#379
b1101 7
18
#380
08
#381
b1110 7
18
#382
08
#383
b1111 7
18
#384
08
b0000000000001100 :
1;
#385
1#
b01100 $
b0000000000001100 &
b0000 7
18
b11111111 <
1>
#386
08
0;
#387
0#
b00000000 '
b00000000 (
b11111111 )
18
b00000000 <
0>
#388
08
#389
b0001 7
18
#390
08
#391
b0010 7
18
b11111111 <
#392
08
#393
b0011 7
18
#394
08
#395
b0100 7
18
b00000000 <
#396
08
#397
b0101 7
18
#398
08
#399
b0110 7
18
#400
08
#401
b0111 7
18
#402
08
#403
b1000 7
18
#404
08
#405
b1001 7
18
#406
08
#407
b1010 7
18
#408
08
#409
b1011 7
18
#410
08
#411
b1100 7
18
#412
08
#413
b1101 7
18
#414
08
#415
b1110 7
18
#416
08
#417
b1111 7
18
#418
08
b0000000000001101 :
1;
#419
1#
b01101 $
b0000000000001101 &
b0000 7
18
1>
#420
08
0;
#421
0#
b11111111 '
18
b11111111 <
0>
#422
08
#423
b0001 7
18
b00000000 <
#424
08
#425
b0010 7
18
b11111111 <
#426
08
#427
b0011 7
18
#428
08
#429
b0100 7
18
b00000000 <
#430
08
#431
b0101 7
18
#432
08
#433
b0110 7
18
#434
08
#435
b0111 7
18
#436
08
#437
b1000 7
18
#438
08
#439
b1001 7
18
#440
08
#441
b1010 7
18
#442
08
#443
b1011 7
18
#444
08
#445
b1100 7
18
#446
08
#447
b1101 7
18
#448
08
#449
b1110 7
18
#450
08
#451
b1111 7
18
#452
08
b0000000000001110 :
1;
#453
1#
b01110 $
b0000000000001110 &
b0000 7
18
b11111111 <
1>
#454
08
0;
#455
0#
b00000000 '
b11111111 (
18
b00000000 <
0>
#456
08
#457
b0001 7
18
b11111111 <
#458
08
#459
b0010 7
18
#460
08
#461
b0011 7
18
#462
08
#463
b0100 7
18
b00000000 <
#464
08
#465
b0101 7
18
#466
08
#467
b0110 7
18
#468
08
#469
b0111 7
18
#470
08
#471
b1000 7
18
#472
08
#473
b1001 7
18
#474
08
#475
b1010 7
18
#476
08
#477
b1011 7
18
#478
08
#479
b1100 7
18
#480
08
#481
b1101 7
18
#482
08
#483
b1110 7
18
#484
08
#485
b1111 7
18
#486
08
b0000000000001111 :
1;
#487
1#
b01111 $
b0000000000001111 &
b0000 7
18
1>
#488
08
0;
#489
0#
b11111111 '
18
b11111111 <
0>
#490
08
#491
b0001 7
18
#492
08
#493
b0010 7
18
#494
08
#495
b0011 7
18
#496
08
#497
b0100 7
18
b00000000 <
#498
08
#499
b0101 7
18
#500
08
#501
b0110 7
18
#502
08
#503
b0111 7
18
#504
08
#505
b1000 7
18
#506
08
#507
b1001 7
18
#508
08
#509
b1010 7
18
#510
08
#511
b1011 7
18
#512
08
#513
b1100 7
18
#514
08
#515
b1101 7
18
#516
08
#517
b1110 7
18
#518
08
#519
b1111 7
18
#520
08
b0000000000010000 :
1;
#521
1#
b10000 $
b0000000000010000 &
b0000 7
18
b11111111 <
1>
#522
08
0;
#523
0#
b00000000 '
b00000000 (
b00000000 )
b00000000 *
b11111111 +
18
b00000000 <
0>
#524
08
#525
b0001 7
18
#526
08
#527
b0010 7
18
#528
08
#529
b0011 7
18
#530
08
#531
b0100 7
18
b11111111 <
#532
08
#533
b0101 7
18
b00000000 <
#534
08
#535
b0110 7
18
#536
08
#537
b0111 7
18
#538
08
#539
b1000 7
18
#540
08
#541
b1001 7
18
#542
08
#543
b1010 7
18
#544
08
#545
b1011 7
18
#546
08
#547
b1100 7
18
#548
08
#549
b1101 7
18
#550
08
#551
b1110 7
18
#552
08
#553
b1111 7
18
#554
08
b0000000000010001 :
1;
#555
1#
b10001 $
b0000000000010001 &
b0000 7
18
1>
#556
08
0;
#557
0#
b11111111 '
18
b11111111 <
0>
#558
08
#559
b0001 7
18
b00000000 <
#560
08
#561
b0010 7
18
#562
08
#563
b0011 7
18
#564
08
#565
b0100 7
18
b11111111 <
#566
08
#567
b0101 7
18
b00000000 <
#568
08
#569
b0110 7
18
#570
08
#571
b0111 7
18
#572
08
#573
b1000 7
18
#574
08
#575
b1001 7
18
#576
08
#577
b1010 7
18
#578
08
#579
b1011 7
18
#580
08
#581
b1100 7
18
#582
08
#583
b1101 7
18
#584
08
#585
b1110 7
18
#586
08
#587
b1111 7
18
#588
08
b0000000000010010 :
1;
#589
1#
b10010 $
b0000000000010010 &
b0000 7
18
b11111111 <
1>
#590
08
0;
#591
0#
b00000000 '
b11111111 (
18
b00000000 <
0>
#592
08
#593
b0001 7
18
b11111111 <
#594
08
#595
b0010 7
18
b00000000 <
#596
08
#597
b0011 7
18
#598
08
#599
b0100 7
18
b11111111 <
#600
08
#601
b0101 7
18
b00000000 <
#602
08
#603
b0110 7
18
#604
08
#605
b0111 7
18
#606
08
#607
b1000 7
18
#608
08
#609
b1001 7
18
#610
08
#611
b1010 7
18
#612
08
#613
b1011 7
18
#614
08
#615
b1100 7
18
#616
08
#617
b1101 7
18
#618
08
#619
b1110 7
18
#620
08
#621
b1111 7
18
#622
08
b0000000000010011 :
1;
#623
1#
b10011 $
b0000000000010011 &
b0000 7
18
1>
#624
08
0;
#625
0#
b11111111 '
18
b11111111 <
0>
#626
08
#627
b0001 7
18
#628
08
#629
b0010 7
18
b00000000 <
#630
08
#631
b0011 7
18
#632
08
#633
b0100 7
18
b11111111 <
#634
08
#635
b0101 7
18
b00000000 <
#636
08
#637
b0110 7
18
#638
08
#639
b0111 7
18
#640
08
#641
b1000 7
18
#642
08
#643
b1001 7
18
#644
08
#645
b1010 7
18
#646
08
#647
b1011 7
18
#648
08
#649
b1100 7
18
#650
08
#651
b1101 7
18
#652
08
#653
b1110 7
18
#654
08
#655
b1111 7
18
#656
08
b0000000000010100 :
1;
