test_run_dir.old/mm2hdmi.MM2hdmiTester536274918/MM2hdmi.v
module MM2hdmi(
  input         clock,
  input         reset,
  input  [15:0] io_data,
  input         io_newData,
  output [7:0]  io_red,
  output [7:0]  io_blue,
  output [7:0]  io_green,
  output        io_vSync,
  output        io_hSync
);
`ifdef RANDOMIZE_REG_INIT
  reg [31:0] _RAND_0;
  reg [31:0] _RAND_1;
  reg [31:0] _RAND_2;
  reg [31:0] _RAND_3;
  reg [31:0] _RAND_4;
  reg [31:0] _RAND_5;
  reg [31:0] _RAND_6;
  reg [31:0] _RAND_7;
  reg [31:0] _RAND_8;
  reg [31:0] _RAND_9;
  reg [31:0] _RAND_10;
  reg [31:0] _RAND_11;
  reg [31:0] _RAND_12;
  reg [31:0] _RAND_13;
  reg [31:0] _RAND_14;
  reg [31:0] _RAND_15;
  reg [31:0] _RAND_16;
  reg [31:0] _RAND_17;
  reg [31:0] _RAND_18;
  reg [31:0] _RAND_19;
  reg [31:0] _RAND_20;
  reg [31:0] _RAND_21;
`endif // RANDOMIZE_REG_INIT
  reg  regNewData; // @[mm2hdmi.scala 19:27]
  reg  regHSync; // @[mm2hdmi.scala 21:25]
  wire  _T_1 = regHSync + 1'h1; // @[mm2hdmi.scala 22:24]
  reg [4:0] regRow; // @[mm2hdmi.scala 24:23]
  wire [4:0] _T_4 = regRow + 5'h1; // @[mm2hdmi.scala 26:22]
  reg  regVSync; // @[mm2hdmi.scala 29:25]
  wire  _T_5 = regRow == 5'h1f; // @[mm2hdmi.scala 30:15]
  wire  _T_7 = _T_5 & io_newData; // @[mm2hdmi.scala 30:24]
  wire  _T_9 = regVSync + 1'h1; // @[mm2hdmi.scala 31:26]
  reg [15:0] regData; // @[mm2hdmi.scala 34:24]
  wire  _T_11 = ~regData[0]; // @[mm2hdmi.scala 36:43]
  reg [7:0] regMuxRed0; // @[mm2hdmi.scala 36:27]
  wire  _T_14 = ~regData[1]; // @[mm2hdmi.scala 37:43]
  reg [7:0] regMuxRed1; // @[mm2hdmi.scala 37:27]
  wire  _T_17 = ~regData[2]; // @[mm2hdmi.scala 38:43]
  reg [7:0] regMuxRed2; // @[mm2hdmi.scala 38:27]
  wire  _T_20 = ~regData[3]; // @[mm2hdmi.scala 39:43]
  reg [7:0] regMuxRed3; // @[mm2hdmi.scala 39:27]
  wire  _T_23 = ~regData[4]; // @[mm2hdmi.scala 40:43]
  reg [7:0] regMuxRed4; // @[mm2hdmi.scala 40:27]
  wire  _T_26 = ~regData[5]; // @[mm2hdmi.scala 41:43]
  reg [7:0] regMuxRed5; // @[mm2hdmi.scala 41:27]
  wire  _T_29 = ~regData[6]; // @[mm2hdmi.scala 42:43]
  reg [7:0] regMuxRed6; // @[mm2hdmi.scala 42:27]
  wire  _T_32 = ~regData[7]; // @[mm2hdmi.scala 43:43]
  reg [7:0] regMuxRed7; // @[mm2hdmi.scala 43:27]
  wire  _T_35 = ~regData[8]; // @[mm2hdmi.scala 44:43]
  reg [7:0] regMuxRed8; // @[mm2hdmi.scala 44:27]
  wire  _T_38 = ~regData[9]; // @[mm2hdmi.scala 45:43]
  reg [7:0] regMuxRed9; // @[mm2hdmi.scala 45:27]
  wire  _T_41 = ~regData[10]; // @[mm2hdmi.scala 46:45]
  reg [7:0] regMuxRed10; // @[mm2hdmi.scala 46:28]
  wire  _T_44 = ~regData[11]; // @[mm2hdmi.scala 47:45]
  reg [7:0] regMuxRed11; // @[mm2hdmi.scala 47:28]
  wire  _T_47 = ~regData[12]; // @[mm2hdmi.scala 48:45]
  reg [7:0] regMuxRed12; // @[mm2hdmi.scala 48:28]
  wire  _T_50 = ~regData[13]; // @[mm2hdmi.scala 49:45]
  reg [7:0] regMuxRed13; // @[mm2hdmi.scala 49:28]
  wire  _T_53 = ~regData[14]; // @[mm2hdmi.scala 50:45]
  reg [7:0] regMuxRed14; // @[mm2hdmi.scala 50:28]
  wire  _T_56 = ~regData[15]; // @[mm2hdmi.scala 51:45]
  reg [7:0] regMuxRed15; // @[mm2hdmi.scala 51:28]
  reg [3:0] outControlCounter; // @[mm2hdmi.scala 53:34]
  wire  _T_58 = outControlCounter == 4'hf; // @[mm2hdmi.scala 54:46]
  wire  _T_60 = _T_58 | regNewData; // @[mm2hdmi.scala 54:55]
  wire [3:0] _T_62 = outControlCounter + 4'h1; // @[mm2hdmi.scala 54:101]
  wire  _T_64 = outControlCounter == 4'h0; // @[mm2hdmi.scala 56:27]
  wire  _T_65 = outControlCounter == 4'h1; // @[mm2hdmi.scala 61:32]
  wire  _T_66 = outControlCounter == 4'h2; // @[mm2hdmi.scala 66:32]
  wire  _T_67 = outControlCounter == 4'h3; // @[mm2hdmi.scala 71:32]
  wire  _T_68 = outControlCounter == 4'h4; // @[mm2hdmi.scala 76:32]
  wire  _T_69 = outControlCounter == 4'h5; // @[mm2hdmi.scala 81:32]
  wire  _T_70 = outControlCounter == 4'h6; // @[mm2hdmi.scala 86:32]
  wire  _T_71 = outControlCounter == 4'h7; // @[mm2hdmi.scala 91:32]
  wire  _T_72 = outControlCounter == 4'h8; // @[mm2hdmi.scala 96:32]
  wire  _T_73 = outControlCounter == 4'h9; // @[mm2hdmi.scala 101:32]
  wire  _T_74 = outControlCounter == 4'ha; // @[mm2hdmi.scala 106:32]
  wire  _T_75 = outControlCounter == 4'hb; // @[mm2hdmi.scala 111:32]
  wire  _T_76 = outControlCounter == 4'hc; // @[mm2hdmi.scala 116:32]
  wire  _T_77 = outControlCounter == 4'hd; // @[mm2hdmi.scala 121:32]
  wire  _T_78 = outControlCounter == 4'he; // @[mm2hdmi.scala 126:32]
  wire [7:0] _GEN_2 = _T_78 ? regMuxRed14 : regMuxRed15; // @[mm2hdmi.scala 126:42]
  wire [7:0] _GEN_3 = _T_77 ? regMuxRed13 : _GEN_2; // @[mm2hdmi.scala 121:42]
  wire [7:0] _GEN_4 = _T_76 ? regMuxRed12 : _GEN_3; // @[mm2hdmi.scala 116:42]
  wire [7:0] _GEN_5 = _T_75 ? regMuxRed11 : _GEN_4; // @[mm2hdmi.scala 111:42]
  wire [7:0] _GEN_6 = _T_74 ? regMuxRed10 : _GEN_5; // @[mm2hdmi.scala 106:42]
  wire [7:0] _GEN_7 = _T_73 ? regMuxRed9 : _GEN_6; // @[mm2hdmi.scala 101:41]
  wire [7:0] _GEN_8 = _T_72 ? regMuxRed8 : _GEN_7; // @[mm2hdmi.scala 96:41]
  wire [7:0] _GEN_9 = _T_71 ? regMuxRed7 : _GEN_8; // @[mm2hdmi.scala 91:41]
  wire [7:0] _GEN_10 = _T_70 ? regMuxRed6 : _GEN_9; // @[mm2hdmi.scala 86:41]
  wire [7:0] _GEN_11 = _T_69 ? regMuxRed5 : _GEN_10; // @[mm2hdmi.scala 81:41]
  wire [7:0] _GEN_12 = _T_68 ? regMuxRed4 : _GEN_11; // @[mm2hdmi.scala 76:41]
  wire [7:0] _GEN_13 = _T_67 ? regMuxRed3 : _GEN_12; // @[mm2hdmi.scala 71:41]
  wire [7:0] _GEN_14 = _T_66 ? regMuxRed2 : _GEN_13; // @[mm2hdmi.scala 66:41]
  wire [7:0] _GEN_15 = _T_65 ? regMuxRed1 : _GEN_14; // @[mm2hdmi.scala 61:41]
  assign io_red = _T_64 ? regMuxRed0 : _GEN_15; // @[mm2hdmi.scala 57:12 mm2hdmi.scala 62:12 mm2hdmi.scala 67:12 mm2hdmi.scala 72:12 mm2hdmi.scala 77:12 mm2hdmi.scala 82:12 mm2hdmi.scala 87:12 mm2hdmi.scala 92:12 mm2hdmi.scala 97:12 mm2hdmi.scala 102:12 mm2hdmi.scala 107:12 mm2hdmi.scala 112:12 mm2hdmi.scala 117:12 mm2hdmi.scala 122:12 mm2hdmi.scala 127:12 mm2hdmi.scala 132:12]
  assign io_blue = _T_64 ? regMuxRed0 : _GEN_15; // @[mm2hdmi.scala 59:13 mm2hdmi.scala 64:13 mm2hdmi.scala 69:13 mm2hdmi.scala 74:13 mm2hdmi.scala 79:13 mm2hdmi.scala 84:13 mm2hdmi.scala 89:13 mm2hdmi.scala 94:13 mm2hdmi.scala 99:13 mm2hdmi.scala 104:13 mm2hdmi.scala 109:13 mm2hdmi.scala 114:13 mm2hdmi.scala 119:13 mm2hdmi.scala 124:13 mm2hdmi.scala 129:13 mm2hdmi.scala 134:13]
  assign io_green = _T_64 ? regMuxRed0 : _GEN_15; // @[mm2hdmi.scala 58:14 mm2hdmi.scala 63:14 mm2hdmi.scala 68:14 mm2hdmi.scala 73:14 mm2hdmi.scala 78:14 mm2hdmi.scala 83:14 mm2hdmi.scala 88:14 mm2hdmi.scala 93:14 mm2hdmi.scala 98:14 mm2hdmi.scala 103:14 mm2hdmi.scala 108:14 mm2hdmi.scala 113:14 mm2hdmi.scala 118:14 mm2hdmi.scala 123:14 mm2hdmi.scala 128:14 mm2hdmi.scala 133:14]
  assign io_vSync = regVSync; // @[mm2hdmi.scala 138:12]
  assign io_hSync = regHSync; // @[mm2hdmi.scala 137:12]
`ifdef RANDOMIZE_GARBAGE_ASSIGN
`define RANDOMIZE
`endif
`ifdef RANDOMIZE_INVALID_ASSIGN
`define RANDOMIZE
`endif
`ifdef RANDOMIZE_REG_INIT
`define RANDOMIZE
`endif
`ifdef RANDOMIZE_MEM_INIT
`define RANDOMIZE
`endif
`ifndef RANDOM
`define RANDOM $random
`endif
`ifdef RANDOMIZE_MEM_INIT
  integer initvar;
`endif
`ifndef SYNTHESIS
`ifdef FIRRTL_BEFORE_INITIAL
`FIRRTL_BEFORE_INITIAL
`endif
initial begin
  `ifdef RANDOMIZE
    `ifdef INIT_RANDOM
      `INIT_RANDOM
    `endif
    `ifndef VERILATOR
      `ifdef RANDOMIZE_DELAY
        #`RANDOMIZE_DELAY begin end
      `else
        #0.002 begin end
      `endif
    `endif
`ifdef RANDOMIZE_REG_INIT
  _RAND_0 = {1{`RANDOM}};
  regNewData = _RAND_0[0:0];
  _RAND_1 = {1{`RANDOM}};
  regHSync = _RAND_1[0:0];
  _RAND_2 = {1{`RANDOM}};
  regRow = _RAND_2[4:0];
  _RAND_3 = {1{`RANDOM}};
  regVSync = _RAND_3[0:0];
  _RAND_4 = {1{`RANDOM}};
  regData = _RAND_4[15:0];
  _RAND_5 = {1{`RANDOM}};
  regMuxRed0 = _RAND_5[7:0];
  _RAND_6 = {1{`RANDOM}};
  regMuxRed1 = _RAND_6[7:0];
  _RAND_7 = {1{`RANDOM}};
  regMuxRed2 = _RAND_7[7:0];
  _RAND_8 = {1{`RANDOM}};
  regMuxRed3 = _RAND_8[7:0];
  _RAND_9 = {1{`RANDOM}};
  regMuxRed4 = _RAND_9[7:0];
  _RAND_10 = {1{`RANDOM}};
  regMuxRed5 = _RAND_10[7:0];
  _RAND_11 = {1{`RANDOM}};
  regMuxRed6 = _RAND_11[7:0];
  _RAND_12 = {1{`RANDOM}};
  regMuxRed7 = _RAND_12[7:0];
  _RAND_13 = {1{`RANDOM}};
  regMuxRed8 = _RAND_13[7:0];
  _RAND_14 = {1{`RANDOM}};
  regMuxRed9 = _RAND_14[7:0];
  _RAND_15 = {1{`RANDOM}};
  regMuxRed10 = _RAND_15[7:0];
  _RAND_16 = {1{`RANDOM}};
  regMuxRed11 = _RAND_16[7:0];
  _RAND_17 = {1{`RANDOM}};
  regMuxRed12 = _RAND_17[7:0];
  _RAND_18 = {1{`RANDOM}};
  regMuxRed13 = _RAND_18[7:0];
  _RAND_19 = {1{`RANDOM}};
  regMuxRed14 = _RAND_19[7:0];
  _RAND_20 = {1{`RANDOM}};
  regMuxRed15 = _RAND_20[7:0];
  _RAND_21 = {1{`RANDOM}};
  outControlCounter = _RAND_21[3:0];
`endif // RANDOMIZE_REG_INIT
  `endif // RANDOMIZE
end // initial
`ifdef FIRRTL_AFTER_INITIAL
`FIRRTL_AFTER_INITIAL
`endif
`endif // SYNTHESIS
  always @(posedge clock) begin
    regNewData <= io_newData;
    if (reset) begin
      regHSync <= 1'h0;
    end else begin
      regHSync <= _T_1;
    end
    if (reset) begin
      regRow <= 5'h0;
    end else if (io_newData) begin
      regRow <= _T_4;
    end
    if (reset) begin
      regVSync <= 1'h0;
    end else if (_T_7) begin
      regVSync <= _T_9;
    end
    regData <= io_data;
    if (_T_11) begin
      regMuxRed0 <= 8'h0;
    end else begin
      regMuxRed0 <= 8'hff;
    end
    if (_T_14) begin
      regMuxRed1 <= 8'h0;
    end else begin
      regMuxRed1 <= 8'hff;
    end
    if (_T_17) begin
      regMuxRed2 <= 8'h0;
    end else begin
      regMuxRed2 <= 8'hff;
    end
    if (_T_20) begin
      regMuxRed3 <= 8'h0;
    end else begin
      regMuxRed3 <= 8'hff;
    end
    if (_T_23) begin
      regMuxRed4 <= 8'h0;
    end else begin
      regMuxRed4 <= 8'hff;
    end
    if (_T_26) begin
      regMuxRed5 <= 8'h0;
    end else begin
      regMuxRed5 <= 8'hff;
    end
    if (_T_29) begin
      regMuxRed6 <= 8'h0;
    end else begin
      regMuxRed6 <= 8'hff;
    end
    if (_T_32) begin
      regMuxRed7 <= 8'h0;
    end else begin
      regMuxRed7 <= 8'hff;
    end
    if (_T_35) begin
      regMuxRed8 <= 8'h0;
    end else begin
      regMuxRed8 <= 8'hff;
    end
    if (_T_38) begin
      regMuxRed9 <= 8'h0;
    end else begin
      regMuxRed9 <= 8'hff;
    end
    if (_T_41) begin
      regMuxRed10 <= 8'h0;
    end else begin
      regMuxRed10 <= 8'hff;
    end
    if (_T_44) begin
      regMuxRed11 <= 8'h0;
    end else begin
      regMuxRed11 <= 8'hff;
    end
    if (_T_47) begin
      regMuxRed12 <= 8'h0;
    end else begin
      regMuxRed12 <= 8'hff;
    end
    if (_T_50) begin
      regMuxRed13 <= 8'h0;
    end else begin
      regMuxRed13 <= 8'hff;
    end
    if (_T_53) begin
      regMuxRed14 <= 8'h0;
    end else begin
      regMuxRed14 <= 8'hff;
    end
    if (_T_56) begin
      regMuxRed15 <= 8'h0;
    end else begin
      regMuxRed15 <= 8'hff;
    end
    if (reset) begin
      outControlCounter <= 4'h0;
    end else if (_T_60) begin
      outControlCounter <= 4'h0;
    end else begin
      outControlCounter <= _T_62;
    end
  end
endmodule

test_run_dir.old/mm2hdmi.MM2hdmiTester536274918/MM2hdmi.vcd
$version Generated by VerilatedVcd $end
$date Mon Nov 30 14:34:22 2020
 $end
$timescale   1ns $end

 $scope module TOP $end
  $var wire  1 9 clock $end
  $var wire  8 > io_blue [7:0] $end
  $var wire 16 ; io_data [15:0] $end
  $var wire  8 ? io_green [7:0] $end
  $var wire  1 A io_hSync $end
  $var wire  1 < io_newData $end
  $var wire  8 = io_red [7:0] $end
  $var wire  1 @ io_vSync $end
  $var wire  1 : reset $end
  $scope module MM2hdmi $end
   $var wire  1 9 clock $end
   $var wire  8 > io_blue [7:0] $end
   $var wire 16 ; io_data [15:0] $end
   $var wire  8 ? io_green [7:0] $end
   $var wire  1 A io_hSync $end
   $var wire  1 < io_newData $end
   $var wire  8 = io_red [7:0] $end
   $var wire  1 @ io_vSync $end
   $var wire  4 8 outControlCounter [3:0] $end
   $var wire 16 ' regData [15:0] $end
   $var wire  1 $ regHSync $end
   $var wire  8 ( regMuxRed0 [7:0] $end
   $var wire  8 ) regMuxRed1 [7:0] $end
   $var wire  8 2 regMuxRed10 [7:0] $end
   $var wire  8 3 regMuxRed11 [7:0] $end
   $var wire  8 4 regMuxRed12 [7:0] $end
   $var wire  8 5 regMuxRed13 [7:0] $end
   $var wire  8 6 regMuxRed14 [7:0] $end
   $var wire  8 7 regMuxRed15 [7:0] $end
   $var wire  8 * regMuxRed2 [7:0] $end
   $var wire  8 + regMuxRed3 [7:0] $end
   $var wire  8 , regMuxRed4 [7:0] $end
   $var wire  8 - regMuxRed5 [7:0] $end
   $var wire  8 . regMuxRed6 [7:0] $end
   $var wire  8 / regMuxRed7 [7:0] $end
   $var wire  8 0 regMuxRed8 [7:0] $end
   $var wire  8 1 regMuxRed9 [7:0] $end
   $var wire  1 # regNewData $end
   $var wire  5 % regRow [4:0] $end
   $var wire  1 & regVSync $end
   $var wire  1 : reset $end
  $upscope $end
 $upscope $end
$enddefinitions $end


#0
0#
0$
b00000 %
0&
b0000000000000000 '
b00000000 (
b00000000 )
b00000000 *
b00000000 +
b00000000 ,
b00000000 -
b00000000 .
b00000000 /
b00000000 0
b00000000 1
b00000000 2
b00000000 3
b00000000 4
b00000000 5
b00000000 6
b00000000 7
b0000 8
09
1:
b0000000000000000 ;
0<
b00000000 =
b00000000 >
b00000000 ?
0@
0A
#1
19
#2
09
#3
19
#4
09
#5
19
#6
09
#7
19
#8
09
#9
19
#10
09
0:
b0000000000001100 ;
1<
#11
1#
1$
b00001 %
b0000000000001100 '
b0001 8
19
1A
#12
09
0<
#13
0#
0$
b11111111 *
b11111111 +
b0000 8
19
0A
#14
09
#15
1$
b0001 8
19
1A
#16
09
#17
0$
b0010 8
19
b11111111 =
b11111111 >
b11111111 ?
0A
#18
09
#19
1$
b0011 8
19
1A
#20
09
#21
0$
b0100 8
19
b00000000 =
b00000000 >
b00000000 ?
0A
#22
09
#23
1$
b0101 8
19
1A
#24
09
#25
0$
b0110 8
19
0A
#26
09
#27
1$
b0111 8
19
1A
#28
09
#29
0$
b1000 8
19
0A
#30
09
#31
1$
b1001 8
19
1A
#32
09
#33
0$
b1010 8
19
0A
#34
09
#35
1$
b1011 8
19
1A
#36
09
#37
0$
b1100 8
19
0A
#38
09
#39
1$
b1101 8
19
1A
#40
09
#41
0$
b1110 8
19
0A
#42
09
#43
1$
b1111 8
19
1A
#44
09
b0000000000001101 ;
1<
#45
1#
0$
b00010 %
b0000000000001101 '
b0000 8
19
0A
#46
09
0<
#47
0#
1$
b11111111 (
19
b11111111 =
b11111111 >
b11111111 ?
1A
#48
09
#49
0$
b0001 8
19
b00000000 =
b00000000 >
b00000000 ?
0A
#50
09
#51
1$
b0010 8
19
b11111111 =
b11111111 >
b11111111 ?
1A
#52
09
#53
0$
b0011 8
19
0A
#54
09
#55
1$
b0100 8
19
b00000000 =
b00000000 >
b00000000 ?
1A
#56
09
#57
0$
b0101 8
19
0A
#58
09
#59
1$
b0110 8
19
1A
#60
09
#61
0$
b0111 8
19
0A
#62
09
#63
1$
b1000 8
19
1A
#64
09
#65
0$
b1001 8
19
0A
#66
09
#67
1$
b1010 8
19
1A
#68
09
#69
0$
b1011 8
19
0A
#70
09
#71
1$
b1100 8
19
1A
#72
09
#73
0$
b1101 8
19
0A
#74
09
#75
1$
b1110 8
19
1A
#76
09
#77
0$
b1111 8
19
0A
#78
09
b0000000000001110 ;
1<
#79
1#
1$
b00011 %
b0000000000001110 '
b0000 8
19
b11111111 =
b11111111 >
b11111111 ?
1A
#80
09
0<
#81
0#
0$
b00000000 (
b11111111 )
19
b00000000 =
b00000000 >
b00000000 ?
0A
#82
09
#83
1$
b0001 8
19
b11111111 =
b11111111 >
b11111111 ?
1A
#84
09
#85
0$
b0010 8
19
0A
#86
09
#87
1$
b0011 8
19
1A
#88
09
#89
0$
b0100 8
19
b00000000 =
b00000000 >
b00000000 ?
0A
#90
09
#91
1$
b0101 8
19
1A
#92
09
#93
0$
b0110 8
19
0A
#94
09
#95
1$
b0111 8
19
1A
#96
09
#97
0$
b1000 8
19
0A
#98
09
#99
1$
b1001 8
19
1A
#100
09
#101
0$
b1010 8
19
0A
#102
09
#103
1$
b1011 8
19
1A
#104
09
#105
0$
b1100 8
19
0A
#106
09
#107
1$
b1101 8
19
1A
#108
09
#109
0$
b1110 8
19
0A
#110
09
#111
1$
b1111 8
19
1A
#112
09
b0000000000001111 ;
1<
#113
1#
0$
b00100 %
b0000000000001111 '
b0000 8
19
0A
#114
09
0<
#115
0#
1$
b11111111 (
19
b11111111 =
b11111111 >
b11111111 ?
1A
#116
09
#117
0$
b0001 8
19
0A
#118
09
#119
1$
b0010 8
19
1A
#120
09
#121
0$
b0011 8
19
0A
#122
09
#123
1$
b0100 8
19
b00000000 =
b00000000 >
b00000000 ?
1A
#124
09
#125
0$
b0101 8
19
0A
#126
09
#127
1$
b0110 8
19
1A
#128
09
#129
0$
b0111 8
19
0A
#130
09
#131
1$
b1000 8
19
1A
#132
09
#133
0$
b1001 8
19
0A
#134
09
#135
1$
b1010 8
19
1A
#136
09
#137
0$
b1011 8
19
0A
#138
09
#139
1$
b1100 8
19
1A
#140
09
#141
0$
b1101 8
19
0A
#142
09
#143
1$
b1110 8
19
1A
#144
09
#145
0$
b1111 8
19
0A
#146
09
b0000000000010000 ;
1<
#147
1#
1$
b00101 %
b0000000000010000 '
b0000 8
19
b11111111 =
b11111111 >
b11111111 ?
1A
#148
09
0<
#149
0#
0$
b00000000 (
b00000000 )
b00000000 *
b00000000 +
b11111111 ,
19
b00000000 =
b00000000 >
b00000000 ?
0A
#150
09
#151
1$
b0001 8
19
1A
#152
09
#153
0$
b0010 8
19
0A
#154
09
#155
1$
b0011 8
19
1A
#156
09
#157
0$
b0100 8
19
b11111111 =
b11111111 >
b11111111 ?
0A
#158
09
#159
1$
b0101 8
19
b00000000 =
b00000000 >
b00000000 ?
1A
#160
09
#161
0$
b0110 8
19
0A
#162
09
#163
1$
b0111 8
19
1A
#164
09
#165
0$
b1000 8
19
0A
#166
09
#167
1$
b1001 8
19
1A
#168
09
#169
0$
b1010 8
19
0A
#170
09
#171
1$
b1011 8
19
1A
#172
09
#173
0$
b1100 8
19
0A
#174
09
#175
1$
b1101 8
19
1A
#176
09
#177
0$
b1110 8
19
0A
#178
09
#179
1$
b1111 8
19
1A
#180
09
b0000000000010001 ;
1<
#181
1#
0$
b00110 %
b0000000000010001 '
b0000 8
19
0A
#182
09
0<
#183
0#
1$
b11111111 (
19
b11111111 =
b11111111 >
b11111111 ?
1A
#184
09
#185
0$
b0001 8
19
b00000000 =
b00000000 >
b00000000 ?
0A
#186
09
#187
1$
b0010 8
19
1A
#188
09
#189
0$
b0011 8
19
0A
#190
09
#191
1$
b0100 8
19
b11111111 =
b11111111 >
b11111111 ?
1A
#192
09
#193
0$
b0101 8
19
b00000000 =
b00000000 >
b00000000 ?
0A
#194
09
#195
1$
b0110 8
19
1A
#196
09
#197
0$
b0111 8
19
0A
#198
09
#199
1$
b1000 8
19
1A
#200
09
#201
0$
b1001 8
19
0A
#202
09
#203
1$
b1010 8
19
1A
#204
09
#205
0$
b1011 8
19
0A
#206
09
#207
1$
b1100 8
19
1A
#208
09
#209
0$
b1101 8
19
0A
#210
09
#211
1$
b1110 8
19
1A
#212
09
#213
0$
b1111 8
19
0A
#214
09
b0000000000010010 ;
1<
#215
1#
1$
b00111 %
b0000000000010010 '
b0000 8
19
b11111111 =
b11111111 >
b11111111 ?
1A
#216
09
0<
#217
0#
0$
b00000000 (
b11111111 )
19
b00000000 =
b00000000 >
b00000000 ?
0A
#218
09
#219
1$
b0001 8
19
b11111111 =
b11111111 >
b11111111 ?
1A
#220
09
#221
0$
b0010 8
19
b00000000 =
b00000000 >
b00000000 ?
0A
#222
09
#223
1$
b0011 8
19
1A
#224
09
#225
0$
b0100 8
19
b11111111 =
b11111111 >
b11111111 ?
0A
#226
09
#227
1$
b0101 8
19
b00000000 =
b00000000 >
b00000000 ?
1A
#228
09
#229
0$
b0110 8
19
0A
#230
09
#231
1$
b0111 8
19
1A
#232
09
#233
0$
b1000 8
19
0A
#234
09
#235
1$
b1001 8
19
1A
#236
09
#237
0$
b1010 8
19
0A
#238
09
#239
1$
b1011 8
19
1A
#240
09
#241
0$
b1100 8
19
0A
#242
09
#243
1$
b1101 8
19
1A
#244
09
#245
0$
b1110 8
19
0A
#246
09
#247
1$
b1111 8
19
1A
#248
09
b0000000000010011 ;
1<
#249
1#
0$
b01000 %
b0000000000010011 '
b0000 8
19
0A
#250
09
0<
#251
0#
1$
b11111111 (
19
b11111111 =
b11111111 >
b11111111 ?
1A
#252
09
#253
0$
b0001 8
19
0A
#254
09
#255
1$
b0010 8
19
b00000000 =
b00000000 >
b00000000 ?
1A
#256
09
#257
0$
b0011 8
19
0A
#258
09
#259
1$
b0100 8
19
b11111111 =
b11111111 >
b11111111 ?
1A
#260
09
#261
0$
b0101 8
19
b00000000 =
b00000000 >
b00000000 ?
0A
#262
09
#263
1$
b0110 8
19
1A
#264
09
#265
0$
b0111 8
19
0A
#266
09
#267
1$
b1000 8
19
1A
#268
09
#269
0$
b1001 8
19
0A
#270
09
#271
1$
b1010 8
19
1A
#272
09
#273
0$
b1011 8
19
0A
#274
09
#275
1$
b1100 8
19
1A
#276
09
#277
0$
b1101 8
19
0A
#278
09
#279
1$
b1110 8
19
1A
#280
09
#281
0$
b1111 8
19
0A
#282
09
b0000000000010100 ;
1<
#283
1#
1$
b01001 %
b0000000000010100 '
b0000 8
19
b11111111 =
b11111111 >
b11111111 ?
1A
#284
09
0<
#285
0#
0$
b00000000 (
b00000000 )
b11111111 *
19
b00000000 =
b00000000 >
b00000000 ?
0A
#286
09
#287
1$
b0001 8
19
1A
#288
09
#289
0$
b0010 8
19
b11111111 =
b11111111 >
b11111111 ?
0A
#290
09
#291
1$
b0011 8
19
b00000000 =
b00000000 >
b00000000 ?
1A
#292
09
#293
0$
b0100 8
19
b11111111 =
b11111111 >
b11111111 ?
0A
#294
09
#295
1$
b0101 8
19
b00000000 =
b00000000 >
b00000000 ?
1A
#296
09
#297
0$
b0110 8
19
0A
#298
09
#299
1$
b0111 8
19
1A
#300
09
#301
0$
b1000 8
19
0A
#302
09
#303
1$
b1001 8
19
1A
#304
09
#305
0$
b1010 8
19
0A
#306
09
#307
1$
b1011 8
19
1A
#308
09
#309
0$
b1100 8
19
0A
#310
09
#311
1$
b1101 8
19
1A
#312
09
#313
0$
b1110 8
19
0A
#314
09
#315
1$
b1111 8
19
1A
#316
09
b0000000000010101 ;
1<
#317
1#
0$
b01010 %
b0000000000010101 '
b0000 8
19
0A
#318
09
0<
#319
0#
1$
b11111111 (
19
b11111111 =
b11111111 >
b11111111 ?
1A
#320
09
#321
0$
b0001 8
19
b00000000 =
b00000000 >
b00000000 ?
0A
#322
09
#323
1$
b0010 8
19
b11111111 =
b11111111 >
b11111111 ?
1A
#324
09
#325
0$
b0011 8
19
b00000000 =
b00000000 >
b00000000 ?
0A
#326
09
#327
1$
b0100 8
19
b11111111 =
b11111111 >
b11111111 ?
1A
#328
09
#329
0$
b0101 8
19
b00000000 =
b00000000 >
b00000000 ?
0A
#330
09
#331
1$
b0110 8
19
1A
#332
09
#333
0$
b0111 8
19
0A
#334
09
#335
1$
b1000 8
19
1A
#336
09
#337
0$
b1001 8
19
0A
#338
09
#339
1$
b1010 8
19
1A
#340
09
#341
0$
b1011 8
19
0A
#342
09
#343
1$
b1100 8
19
1A
#344
09
#345
0$
b1101 8
19
0A
#346
09
#347
1$
b1110 8
19
1A
#348
09
#349
0$
b1111 8
19
0A
#350
09
b0000000000010110 ;
1<
#351
1#
1$
b01011 %
b0000000000010110 '
b0000 8
19
b11111111 =
b11111111 >
b11111111 ?
1A
#352
09
0<
#353
0#
0$
b00000000 (
b11111111 )
19
b00000000 =
b00000000 >
b00000000 ?
0A
#354
09
#355
1$
b0001 8
19
b11111111 =
b11111111 >
b11111111 ?
1A
#356
09
#357
0$
b0010 8
19
0A
#358
09
#359
1$
b0011 8
19
b00000000 =
b00000000 >
b00000000 ?
1A
#360
09
#361
0$
b0100 8
19
b11111111 =
b11111111 >
b11111111 ?
0A
#362
09
#363
1$
b0101 8
19
b00000000 =
b00000000 >
b00000000 ?
1A
#364
09
#365
0$
b0110 8
19
0A
#366
09
#367
1$
b0111 8
19
1A
#368
09
#369
0$
b1000 8
19
0A
#370
09
#371
1$
b1001 8
19
1A
#372
09
#373
0$
b1010 8
19
0A
#374
09
#375
1$
b1011 8
19
1A
#376
09
#377
0$
b1100 8
19
0A
#378
09
#379
1$
b1101 8
19
1A
#380
09
#381
0$
b1110 8
19
0A
#382
09
#383
1$
b1111 8
19
1A
#384
09
b0000000000010111 ;
1<
#385
1#
0$
b01100 %
b0000000000010111 '
b0000 8
19
0A
#386
09
0<
#387
0#
1$
b11111111 (
19
b11111111 =
b11111111 >
b11111111 ?
1A
#388
09
#389
0$
b0001 8
19
0A
#390
09
#391
1$
b0010 8
19
1A
#392
09
#393
0$
b0011 8
19
b00000000 =
b00000000 >
b00000000 ?
0A
#394
09
#395
1$
b0100 8
19
b11111111 =
b11111111 >
b11111111 ?
1A
#396
09
#397
0$
b0101 8
19
b00000000 =
b00000000 >
b00000000 ?
0A
#398
09
#399
1$
b0110 8
19
1A
#400
09
#401
0$
b0111 8
19
0A
#402
09
#403
1$
b1000 8
19
1A
#404
09
#405
0$
b1001 8
19
0A
#406
09
#407
1$
b1010 8
19
1A
#408
09
#409
0$
b1011 8
19
0A
#410
09
#411
1$
b1100 8
19
1A
#412
09
#413
0$
b1101 8
19
0A
#414
09
#415
1$
b1110 8
19
1A
#416
09
#417
0$
b1111 8
19
0A
#418
09
b0000000000011000 ;
1<
#419
1#
1$
b01101 %
b0000000000011000 '
b0000 8
19
b11111111 =
b11111111 >
b11111111 ?
1A
#420
09
0<
#421
0#
0$
b00000000 (
b00000000 )
b00000000 *
b11111111 +
19
b00000000 =
b00000000 >
b00000000 ?
0A
#422
09
#423
1$
b0001 8
19
1A
#424
09
#425
0$
b0010 8
19
0A
#426
09
#427
1$
b0011 8
19
b11111111 =
b11111111 >
b11111111 ?
1A
#428
09
#429
0$
b0100 8
19
0A
#430
09
#431
1$
b0101 8
19
b00000000 =
b00000000 >
b00000000 ?
1A
#432
09
#433
0$
b0110 8
19
0A
#434
09
#435
1$
b0111 8
19
1A
#436
09
#437
0$
b1000 8
19
0A
#438
09
#439
1$
b1001 8
19
1A
#440
09
#441
0$
b1010 8
19
0A
#442
09
