test_run_dir.old/mm2hdmi.MM2hdmiTester1621435857/MM2hdmi.v
module MM2hdmi(
  input         clock,
  input         reset,
  input  [15:0] io_data,
  input  [15:0] io_address,
  input         io_newData,
  output [7:0]  io_red,
  output [7:0]  io_blue,
  output [7:0]  io_green,
  output        io_vSync,
  output        io_hSync
);
`ifdef RANDOMIZE_REG_INIT
  reg [31:0] _RAND_0;
  reg [31:0] _RAND_1;
  reg [31:0] _RAND_2;
  reg [31:0] _RAND_3;
  reg [31:0] _RAND_4;
  reg [31:0] _RAND_5;
  reg [31:0] _RAND_6;
  reg [31:0] _RAND_7;
  reg [31:0] _RAND_8;
  reg [31:0] _RAND_9;
  reg [31:0] _RAND_10;
  reg [31:0] _RAND_11;
  reg [31:0] _RAND_12;
  reg [31:0] _RAND_13;
  reg [31:0] _RAND_14;
  reg [31:0] _RAND_15;
  reg [31:0] _RAND_16;
  reg [31:0] _RAND_17;
  reg [31:0] _RAND_18;
  reg [31:0] _RAND_19;
  reg [31:0] _RAND_20;
  reg [31:0] _RAND_21;
`endif // RANDOMIZE_REG_INIT
  reg  regNewData; // @[mm2hdmi.scala 20:27]
  reg  regHSync; // @[mm2hdmi.scala 22:25]
  wire  _T_1 = regHSync + 1'h1; // @[mm2hdmi.scala 23:24]
  reg [4:0] regRow; // @[mm2hdmi.scala 25:23]
  wire [4:0] _T_4 = regRow + 5'h1; // @[mm2hdmi.scala 27:22]
  reg  regVSync; // @[mm2hdmi.scala 30:25]
  wire [5:0] _GEN_17 = {{1'd0}, regRow}; // @[mm2hdmi.scala 31:15]
  wire  _T_5 = _GEN_17 == 6'h20; // @[mm2hdmi.scala 31:15]
  wire  _T_7 = regVSync + 1'h1; // @[mm2hdmi.scala 32:26]
  reg [15:0] regData; // @[mm2hdmi.scala 37:24]
  wire  _T_9 = ~regData[0]; // @[mm2hdmi.scala 39:43]
  reg [7:0] regMuxRed0; // @[mm2hdmi.scala 39:27]
  wire  _T_12 = ~regData[1]; // @[mm2hdmi.scala 40:43]
  reg [7:0] regMuxRed1; // @[mm2hdmi.scala 40:27]
  wire  _T_15 = ~regData[2]; // @[mm2hdmi.scala 41:43]
  reg [7:0] regMuxRed2; // @[mm2hdmi.scala 41:27]
  wire  _T_18 = ~regData[3]; // @[mm2hdmi.scala 42:43]
  reg [7:0] regMuxRed3; // @[mm2hdmi.scala 42:27]
  wire  _T_21 = ~regData[4]; // @[mm2hdmi.scala 43:43]
  reg [7:0] regMuxRed4; // @[mm2hdmi.scala 43:27]
  wire  _T_24 = ~regData[5]; // @[mm2hdmi.scala 44:43]
  reg [7:0] regMuxRed5; // @[mm2hdmi.scala 44:27]
  wire  _T_27 = ~regData[6]; // @[mm2hdmi.scala 45:43]
  reg [7:0] regMuxRed6; // @[mm2hdmi.scala 45:27]
  wire  _T_30 = ~regData[7]; // @[mm2hdmi.scala 46:43]
  reg [7:0] regMuxRed7; // @[mm2hdmi.scala 46:27]
  wire  _T_33 = ~regData[8]; // @[mm2hdmi.scala 47:43]
  reg [7:0] regMuxRed8; // @[mm2hdmi.scala 47:27]
  wire  _T_36 = ~regData[9]; // @[mm2hdmi.scala 48:43]
  reg [7:0] regMuxRed9; // @[mm2hdmi.scala 48:27]
  wire  _T_39 = ~regData[10]; // @[mm2hdmi.scala 49:45]
  reg [7:0] regMuxRed10; // @[mm2hdmi.scala 49:28]
  wire  _T_42 = ~regData[11]; // @[mm2hdmi.scala 50:45]
  reg [7:0] regMuxRed11; // @[mm2hdmi.scala 50:28]
  wire  _T_45 = ~regData[12]; // @[mm2hdmi.scala 51:45]
  reg [7:0] regMuxRed12; // @[mm2hdmi.scala 51:28]
  wire  _T_48 = ~regData[13]; // @[mm2hdmi.scala 52:45]
  reg [7:0] regMuxRed13; // @[mm2hdmi.scala 52:28]
  wire  _T_51 = ~regData[14]; // @[mm2hdmi.scala 53:45]
  reg [7:0] regMuxRed14; // @[mm2hdmi.scala 53:28]
  wire  _T_54 = ~regData[15]; // @[mm2hdmi.scala 54:45]
  reg [7:0] regMuxRed15; // @[mm2hdmi.scala 54:28]
  reg [3:0] outControlCounter; // @[mm2hdmi.scala 56:34]
  wire  _T_56 = outControlCounter == 4'hf; // @[mm2hdmi.scala 57:46]
  wire  _T_58 = _T_56 | regNewData; // @[mm2hdmi.scala 57:55]
  wire [3:0] _T_60 = outControlCounter + 4'h1; // @[mm2hdmi.scala 57:101]
  wire  _T_62 = outControlCounter == 4'h0; // @[mm2hdmi.scala 59:27]
  wire  _T_63 = outControlCounter == 4'h1; // @[mm2hdmi.scala 64:32]
  wire  _T_64 = outControlCounter == 4'h2; // @[mm2hdmi.scala 69:32]
  wire  _T_65 = outControlCounter == 4'h3; // @[mm2hdmi.scala 74:32]
  wire  _T_66 = outControlCounter == 4'h4; // @[mm2hdmi.scala 79:32]
  wire  _T_67 = outControlCounter == 4'h5; // @[mm2hdmi.scala 84:32]
  wire  _T_68 = outControlCounter == 4'h6; // @[mm2hdmi.scala 89:32]
  wire  _T_69 = outControlCounter == 4'h7; // @[mm2hdmi.scala 94:32]
  wire  _T_70 = outControlCounter == 4'h8; // @[mm2hdmi.scala 99:32]
  wire  _T_71 = outControlCounter == 4'h9; // @[mm2hdmi.scala 104:32]
  wire  _T_72 = outControlCounter == 4'ha; // @[mm2hdmi.scala 109:32]
  wire  _T_73 = outControlCounter == 4'hb; // @[mm2hdmi.scala 114:32]
  wire  _T_74 = outControlCounter == 4'hc; // @[mm2hdmi.scala 119:32]
  wire  _T_75 = outControlCounter == 4'hd; // @[mm2hdmi.scala 124:32]
  wire  _T_76 = outControlCounter == 4'he; // @[mm2hdmi.scala 129:32]
  wire [7:0] _GEN_2 = _T_76 ? regMuxRed14 : regMuxRed15; // @[mm2hdmi.scala 129:42]
  wire [7:0] _GEN_3 = _T_75 ? regMuxRed13 : _GEN_2; // @[mm2hdmi.scala 124:42]
  wire [7:0] _GEN_4 = _T_74 ? regMuxRed12 : _GEN_3; // @[mm2hdmi.scala 119:42]
  wire [7:0] _GEN_5 = _T_73 ? regMuxRed11 : _GEN_4; // @[mm2hdmi.scala 114:42]
  wire [7:0] _GEN_6 = _T_72 ? regMuxRed10 : _GEN_5; // @[mm2hdmi.scala 109:42]
  wire [7:0] _GEN_7 = _T_71 ? regMuxRed9 : _GEN_6; // @[mm2hdmi.scala 104:41]
  wire [7:0] _GEN_8 = _T_70 ? regMuxRed8 : _GEN_7; // @[mm2hdmi.scala 99:41]
  wire [7:0] _GEN_9 = _T_69 ? regMuxRed7 : _GEN_8; // @[mm2hdmi.scala 94:41]
  wire [7:0] _GEN_10 = _T_68 ? regMuxRed6 : _GEN_9; // @[mm2hdmi.scala 89:41]
  wire [7:0] _GEN_11 = _T_67 ? regMuxRed5 : _GEN_10; // @[mm2hdmi.scala 84:41]
  wire [7:0] _GEN_12 = _T_66 ? regMuxRed4 : _GEN_11; // @[mm2hdmi.scala 79:41]
  wire [7:0] _GEN_13 = _T_65 ? regMuxRed3 : _GEN_12; // @[mm2hdmi.scala 74:41]
  wire [7:0] _GEN_14 = _T_64 ? regMuxRed2 : _GEN_13; // @[mm2hdmi.scala 69:41]
  wire [7:0] _GEN_15 = _T_63 ? regMuxRed1 : _GEN_14; // @[mm2hdmi.scala 64:41]
  assign io_red = _T_62 ? regMuxRed0 : _GEN_15; // @[mm2hdmi.scala 60:12 mm2hdmi.scala 65:12 mm2hdmi.scala 70:12 mm2hdmi.scala 75:12 mm2hdmi.scala 80:12 mm2hdmi.scala 85:12 mm2hdmi.scala 90:12 mm2hdmi.scala 95:12 mm2hdmi.scala 100:12 mm2hdmi.scala 105:12 mm2hdmi.scala 110:12 mm2hdmi.scala 115:12 mm2hdmi.scala 120:12 mm2hdmi.scala 125:12 mm2hdmi.scala 130:12 mm2hdmi.scala 135:12]
  assign io_blue = _T_62 ? regMuxRed0 : _GEN_15; // @[mm2hdmi.scala 62:13 mm2hdmi.scala 67:13 mm2hdmi.scala 72:13 mm2hdmi.scala 77:13 mm2hdmi.scala 82:13 mm2hdmi.scala 87:13 mm2hdmi.scala 92:13 mm2hdmi.scala 97:13 mm2hdmi.scala 102:13 mm2hdmi.scala 107:13 mm2hdmi.scala 112:13 mm2hdmi.scala 117:13 mm2hdmi.scala 122:13 mm2hdmi.scala 127:13 mm2hdmi.scala 132:13 mm2hdmi.scala 137:13]
  assign io_green = _T_62 ? regMuxRed0 : _GEN_15; // @[mm2hdmi.scala 61:14 mm2hdmi.scala 66:14 mm2hdmi.scala 71:14 mm2hdmi.scala 76:14 mm2hdmi.scala 81:14 mm2hdmi.scala 86:14 mm2hdmi.scala 91:14 mm2hdmi.scala 96:14 mm2hdmi.scala 101:14 mm2hdmi.scala 106:14 mm2hdmi.scala 111:14 mm2hdmi.scala 116:14 mm2hdmi.scala 121:14 mm2hdmi.scala 126:14 mm2hdmi.scala 131:14 mm2hdmi.scala 136:14]
  assign io_vSync = regVSync; // @[mm2hdmi.scala 141:12]
  assign io_hSync = regHSync; // @[mm2hdmi.scala 140:12]
`ifdef RANDOMIZE_GARBAGE_ASSIGN
`define RANDOMIZE
`endif
`ifdef RANDOMIZE_INVALID_ASSIGN
`define RANDOMIZE
`endif
`ifdef RANDOMIZE_REG_INIT
`define RANDOMIZE
`endif
`ifdef RANDOMIZE_MEM_INIT
`define RANDOMIZE
`endif
`ifndef RANDOM
`define RANDOM $random
`endif
`ifdef RANDOMIZE_MEM_INIT
  integer initvar;
`endif
`ifndef SYNTHESIS
`ifdef FIRRTL_BEFORE_INITIAL
`FIRRTL_BEFORE_INITIAL
`endif
initial begin
  `ifdef RANDOMIZE
    `ifdef INIT_RANDOM
      `INIT_RANDOM
    `endif
    `ifndef VERILATOR
      `ifdef RANDOMIZE_DELAY
        #`RANDOMIZE_DELAY begin end
      `else
        #0.002 begin end
      `endif
    `endif
`ifdef RANDOMIZE_REG_INIT
  _RAND_0 = {1{`RANDOM}};
  regNewData = _RAND_0[0:0];
  _RAND_1 = {1{`RANDOM}};
  regHSync = _RAND_1[0:0];
  _RAND_2 = {1{`RANDOM}};
  regRow = _RAND_2[4:0];
  _RAND_3 = {1{`RANDOM}};
  regVSync = _RAND_3[0:0];
  _RAND_4 = {1{`RANDOM}};
  regData = _RAND_4[15:0];
  _RAND_5 = {1{`RANDOM}};
  regMuxRed0 = _RAND_5[7:0];
  _RAND_6 = {1{`RANDOM}};
  regMuxRed1 = _RAND_6[7:0];
  _RAND_7 = {1{`RANDOM}};
  regMuxRed2 = _RAND_7[7:0];
  _RAND_8 = {1{`RANDOM}};
  regMuxRed3 = _RAND_8[7:0];
  _RAND_9 = {1{`RANDOM}};
  regMuxRed4 = _RAND_9[7:0];
  _RAND_10 = {1{`RANDOM}};
  regMuxRed5 = _RAND_10[7:0];
  _RAND_11 = {1{`RANDOM}};
  regMuxRed6 = _RAND_11[7:0];
  _RAND_12 = {1{`RANDOM}};
  regMuxRed7 = _RAND_12[7:0];
  _RAND_13 = {1{`RANDOM}};
  regMuxRed8 = _RAND_13[7:0];
  _RAND_14 = {1{`RANDOM}};
  regMuxRed9 = _RAND_14[7:0];
  _RAND_15 = {1{`RANDOM}};
  regMuxRed10 = _RAND_15[7:0];
  _RAND_16 = {1{`RANDOM}};
  regMuxRed11 = _RAND_16[7:0];
  _RAND_17 = {1{`RANDOM}};
  regMuxRed12 = _RAND_17[7:0];
  _RAND_18 = {1{`RANDOM}};
  regMuxRed13 = _RAND_18[7:0];
  _RAND_19 = {1{`RANDOM}};
  regMuxRed14 = _RAND_19[7:0];
  _RAND_20 = {1{`RANDOM}};
  regMuxRed15 = _RAND_20[7:0];
  _RAND_21 = {1{`RANDOM}};
  outControlCounter = _RAND_21[3:0];
`endif // RANDOMIZE_REG_INIT
  `endif // RANDOMIZE
end // initial
`ifdef FIRRTL_AFTER_INITIAL
`FIRRTL_AFTER_INITIAL
`endif
`endif // SYNTHESIS
  always @(posedge clock) begin
    regNewData <= io_newData;
    if (reset) begin
      regHSync <= 1'h0;
    end else begin
      regHSync <= _T_1;
    end
    if (reset) begin
      regRow <= 5'h0;
    end else if (io_newData) begin
      regRow <= _T_4;
    end
    if (reset) begin
      regVSync <= 1'h0;
    end else if (_T_5) begin
      regVSync <= _T_7;
    end
    regData <= io_data;
    if (_T_9) begin
      regMuxRed0 <= 8'h0;
    end else begin
      regMuxRed0 <= 8'hff;
    end
    if (_T_12) begin
      regMuxRed1 <= 8'h0;
    end else begin
      regMuxRed1 <= 8'hff;
    end
    if (_T_15) begin
      regMuxRed2 <= 8'h0;
    end else begin
      regMuxRed2 <= 8'hff;
    end
    if (_T_18) begin
      regMuxRed3 <= 8'h0;
    end else begin
      regMuxRed3 <= 8'hff;
    end
    if (_T_21) begin
      regMuxRed4 <= 8'h0;
    end else begin
      regMuxRed4 <= 8'hff;
    end
    if (_T_24) begin
      regMuxRed5 <= 8'h0;
    end else begin
      regMuxRed5 <= 8'hff;
    end
    if (_T_27) begin
      regMuxRed6 <= 8'h0;
    end else begin
      regMuxRed6 <= 8'hff;
    end
    if (_T_30) begin
      regMuxRed7 <= 8'h0;
    end else begin
      regMuxRed7 <= 8'hff;
    end
    if (_T_33) begin
      regMuxRed8 <= 8'h0;
    end else begin
      regMuxRed8 <= 8'hff;
    end
    if (_T_36) begin
      regMuxRed9 <= 8'h0;
    end else begin
      regMuxRed9 <= 8'hff;
    end
    if (_T_39) begin
      regMuxRed10 <= 8'h0;
    end else begin
      regMuxRed10 <= 8'hff;
    end
    if (_T_42) begin
      regMuxRed11 <= 8'h0;
    end else begin
      regMuxRed11 <= 8'hff;
    end
    if (_T_45) begin
      regMuxRed12 <= 8'h0;
    end else begin
      regMuxRed12 <= 8'hff;
    end
    if (_T_48) begin
      regMuxRed13 <= 8'h0;
    end else begin
      regMuxRed13 <= 8'hff;
    end
    if (_T_51) begin
      regMuxRed14 <= 8'h0;
    end else begin
      regMuxRed14 <= 8'hff;
    end
    if (_T_54) begin
      regMuxRed15 <= 8'h0;
    end else begin
      regMuxRed15 <= 8'hff;
    end
    if (reset) begin
      outControlCounter <= 4'h0;
    end else if (_T_58) begin
      outControlCounter <= 4'h0;
    end else begin
      outControlCounter <= _T_60;
    end
  end
endmodule

test_run_dir.old/mm2hdmi.MM2hdmiTester1621435857/MM2hdmi.vcd
$version Generated by VerilatedVcd $end
$date Mon Nov 30 14:23:14 2020
 $end
$timescale   1ns $end

 $scope module TOP $end
  $var wire  1 9 clock $end
  $var wire 16 < io_address [15:0] $end
  $var wire  8 ? io_blue [7:0] $end
  $var wire 16 ; io_data [15:0] $end
  $var wire  8 @ io_green [7:0] $end
  $var wire  1 B io_hSync $end
  $var wire  1 = io_newData $end
  $var wire  8 > io_red [7:0] $end
  $var wire  1 A io_vSync $end
  $var wire  1 : reset $end
  $scope module MM2hdmi $end
   $var wire  1 9 clock $end
   $var wire 16 < io_address [15:0] $end
   $var wire  8 ? io_blue [7:0] $end
   $var wire 16 ; io_data [15:0] $end
   $var wire  8 @ io_green [7:0] $end
   $var wire  1 B io_hSync $end
   $var wire  1 = io_newData $end
   $var wire  8 > io_red [7:0] $end
   $var wire  1 A io_vSync $end
   $var wire  4 8 outControlCounter [3:0] $end
   $var wire 16 ' regData [15:0] $end
   $var wire  1 $ regHSync $end
   $var wire  8 ( regMuxRed0 [7:0] $end
   $var wire  8 ) regMuxRed1 [7:0] $end
   $var wire  8 2 regMuxRed10 [7:0] $end
   $var wire  8 3 regMuxRed11 [7:0] $end
   $var wire  8 4 regMuxRed12 [7:0] $end
   $var wire  8 5 regMuxRed13 [7:0] $end
   $var wire  8 6 regMuxRed14 [7:0] $end
   $var wire  8 7 regMuxRed15 [7:0] $end
   $var wire  8 * regMuxRed2 [7:0] $end
   $var wire  8 + regMuxRed3 [7:0] $end
   $var wire  8 , regMuxRed4 [7:0] $end
   $var wire  8 - regMuxRed5 [7:0] $end
   $var wire  8 . regMuxRed6 [7:0] $end
   $var wire  8 / regMuxRed7 [7:0] $end
   $var wire  8 0 regMuxRed8 [7:0] $end
   $var wire  8 1 regMuxRed9 [7:0] $end
   $var wire  1 # regNewData $end
   $var wire  5 % regRow [4:0] $end
   $var wire  1 & regVSync $end
   $var wire  1 : reset $end
  $upscope $end
 $upscope $end
$enddefinitions $end


#0
0#
0$
b00000 %
0&
b0000000000000000 '
b00000000 (
b00000000 )
b00000000 *
b00000000 +
b00000000 ,
b00000000 -
b00000000 .
b00000000 /
b00000000 0
b00000000 1
b00000000 2
b00000000 3
b00000000 4
b00000000 5
b00000000 6
b00000000 7
b0000 8
09
1:
b0000000000000000 ;
b0000000000000000 <
0=
b00000000 >
b00000000 ?
b00000000 @
0A
0B
#1
19
#2
09
#3
19
#4
09
#5
19
#6
09
#7
19
#8
09
#9
19
#10
09
0:
b0000000000001100 ;
1=
#11
1#
1$
b00001 %
b0000000000001100 '
b0001 8
19
1B
#12
09
0=
#13
0#
0$
b11111111 *
b11111111 +
b0000 8
19
0B
#14
09
#15
1$
b0001 8
19
1B
#16
09
#17
0$
b0010 8
19
b11111111 >
b11111111 ?
b11111111 @
0B
#18
09
#19
1$
b0011 8
19
1B
#20
09
#21
0$
b0100 8
19
b00000000 >
b00000000 ?
b00000000 @
0B
#22
09
#23
1$
b0101 8
19
1B
#24
09
#25
0$
b0110 8
19
0B
#26
09
#27
1$
b0111 8
19
1B
#28
09
#29
0$
b1000 8
19
0B
#30
09
#31
1$
b1001 8
19
1B
#32
09
#33
0$
b1010 8
19
0B
#34
09
#35
1$
b1011 8
19
1B
#36
09
#37
0$
b1100 8
19
0B
#38
09
#39
1$
b1101 8
19
1B
#40
09
#41
0$
b1110 8
19
0B
#42
09
#43
1$
b1111 8
19
1B
#44
09
b0000000000111111 ;
1=
#45
1#
0$
b00010 %
b0000000000111111 '
b0000 8
19
0B
#46
09
0=
#47
0#
1$
b11111111 (
b11111111 )
b11111111 ,
b11111111 -
19
b11111111 >
b11111111 ?
b11111111 @
1B
#48
09
#49
0$
b0001 8
19
0B
#50
09
#51
1$
b0010 8
19
1B
#52
09
#53
0$
b0011 8
19
0B
#54
09
#55
1$
b0100 8
19
1B
#56
09
#57
0$
b0101 8
19
0B
#58
09
#59
1$
b0110 8
19
b00000000 >
b00000000 ?
b00000000 @
1B
#60
09
#61
0$
b0111 8
19
0B
#62
09
#63
1$
b1000 8
19
1B
#64
09
#65
0$
b1001 8
19
0B
#66
09
#67
1$
b1010 8
19
1B
#68
09
#69
0$
b1011 8
19
0B
#70
09
#71
1$
b1100 8
19
1B
#72
09
#73
0$
b1101 8
19
0B
#74
09
#75
1$
b1110 8
19
1B
#76
09
#77
0$
b1111 8
19
0B
